{
  "$schema": "../node_modules/@tauri-apps/cli/config.schema.json",
  "productName": "CLiP BOOsT Website",
  "version": "0.1.0",
  "identifier": "com.clipboost.website",
  "build": {
    "frontendDist": "../dist",
    "devUrl": "http://localhost:5173",
    "beforeDevCommand": "npm run dev",
    "beforeBuildCommand": "npm run build"
  },
  "app": {
    "windows": [
      {
        "title": "CLiP BOOsT",
        "width": 1280,
        "height": 820,
        "minWidth": 1100,
        "minHeight": 700,
        "resizable": true,
        "fullscreen": false
      }
    ],
    "security": {
      "csp": null
    }
  },
  "bundle": {
    "active": true,
    "targets": "all",
    "icon": []
  }
}
